{
  "rooms": [
    {
      "id": "639bc4d83b867100010cf851",
      "ownerID": "639af2c9c6355b1cd52fe516",
      "owner": {
        "userID": "639af2c9c6355b1cd52fe516",
        "displayName": "Apolostudios / Metaverse Developer"
      },
      "name": "Plaza Mayor Valladolid (Spain)-  Ferias y Fiestas Virgen San Lorenzo 2023",
      "slug": "Plaza-Mayor-Valladolid-Spain-Ferias-y-Fiestas-Virgen-San-Lorenzo-2023",
      "description": "Vive en directo el pregón, el record guiness y el espectaculo piromusical de las ferias y fiestas de Valladolid.",
      "tags": [
        "valladolid",
        "trendy",
        "party",
        "turism",
        "spain"
      ],
      "orgOwner": {
        "id": "",
        "name": "",
        "subscription": {
          "subscriptionType": "",
          "subscriptionSource": "",
          "isActive": false
        }
      },
      "organizations": null,
      "timeLastJoined": "0001-01-01T00:00:00Z",
      "thumbnails": [],
      "activeParticipants": [
        {
          "id": "6494e59c00755e71b831b155",
          "displayName": "백인규",
          "profilePicURL": "https://renderapi.s3.amazonaws.com/npMsrGr2P.png",
          "avatarData": {
            "avatarUserID": "",
            "avatarID": "",
            "avatarBody": "https://dd2cgqlmnwvp5.cloudfront.net/avatar_generic_bodies/rpm_female_hijab/model.glb",
            "filename": "",
            "skinColorOverride": "",
            "shirtColorOverride": "",
            "readyPlayerMeID": "",
            "readyPlayerMeAvatarID": "",
            "readyPlayerMeThumbnails": {
              "upperBody": "https://renderapi.s3.amazonaws.com/npMsrGr2P.png",
              "lowerBody": ""
            },
            "readyPlayerMeUrl": "https://models.readyplayer.me/6494e7278f691ae17c75defb.glb?updatedAt=1687480542047",
            "ReadyPlayerMeUrlLastUpdated": "0001-01-01T00:00:00Z",
            "readyPlayerMeUrlCrunched": "",
            "readyPlayerMeUrlCrunchedBrotli": "",
            "ReadyPlayerMeUrlCrunchedLastUpdated": "0001-01-01T00:00:00Z",
            "activeAvatarStyle": "READY_PLAYER_ME"
          },
          "appearanceCustomization": {
            "profileColor": "orange"
          },
          "clientPlatforms": [
            "Android"
          ],
          "permissions": []
        },
        {
          "id": "650bcbd3997987b22b0b5785",
          "displayName": "nozawa",
          "profilePicURL": "",
          "avatarData": {
            "avatarUserID": "",
            "avatarID": "",
            "avatarBody": "",
            "filename": "",
            "skinColorOverride": "",
            "shirtColorOverride": "",
            "readyPlayerMeID": "",
            "readyPlayerMeAvatarID": "",
            "readyPlayerMeThumbnails": {
              "upperBody": "",
              "lowerBody": ""
            },
            "readyPlayerMeUrl": "",
            "ReadyPlayerMeUrlLastUpdated": "0001-01-01T00:00:00Z",
            "readyPlayerMeUrlCrunched": "",
            "readyPlayerMeUrlCrunchedBrotli": "",
            "ReadyPlayerMeUrlCrunchedLastUpdated": "0001-01-01T00:00:00Z",
            "activeAvatarStyle": "REALISTIC"
          },
          "appearanceCustomization": {
            "profileColor": "teal"
          },
          "clientPlatforms": [
            "Web"
          ],
          "permissions": []
        }
      ],
      "polymerVersion": 19,
      "roomThumbnails": {
        "customGetUrl": "https://cdn.spatial.io/assets/v1/thumbnails/639bc4d83b867100010cf851/customThumbnail/r/5b13dab3bdfc1ade295093835929d9b6ba4517481ce99e67970d6a866b66a568/1695273823",
        "transientGetUrl": "https://cdn.spatial.io/assets/v1/thumbnails/639bc4d83b867100010cf851/transientStateThumbnail/r/befd74e560ba3c9052dbcff72bc2e6e03c49f1b585a3f54a0d18c0ba50598449/1695273823",
        "persistentGetUrl": "https://cdn.spatial.io/assets/v1/thumbnails/639bc4d83b867100010cf851/persistentStateThumbnail/r/8662c5de537169420bd4792f7e0f2678cd59f88070064f9cb6ebab35a5159111/1695273823",
        "cubemapGetUrl": "https://cdn.spatial.io/assets/v1/thumbnails/639bc4d83b867100010cf851/cubemap/r/a3093473275e9ea043e21b36e72ac5c325b3e2ef69f3f827b3b5e2f07f4d5207/1695273823",
        "expiresAt": 1695288251
      },
      "thumbnail": "https://cdn.spatial.io/assets/v1/thumbnails/639bc4d83b867100010cf851/customThumbnail/r/5b13dab3bdfc1ade295093835929d9b6ba4517481ce99e67970d6a866b66a568/1695273823",
      "cubeMap": "https://cdn.spatial.io/assets/v1/thumbnails/639bc4d83b867100010cf851/cubemap/r/a3093473275e9ea043e21b36e72ac5c325b3e2ef69f3f827b3b5e2f07f4d5207/1695273823",
      "starred": true,
      "sandbox": false,
      "shareID": "6871682445212284257",
      "code": "",
      "shareSetting": "ORG",
      "publicLink": true,
      "roomAdmins": [
        "62cfe0d21111938e99737620",
        "62cffe2bb921b8527a6a4007"
      ],
      "restrictedPermissions": [
        "RESTRICT_OTHERS_VIEW_ONLY"
      ],
      "directlyInvitedGuests": {},
      "lobbyType": "",
      "published": true,
      "defaultRoomContent": null,
      "accessible": true,
      "createdAt": "2022-12-16T01:07:36.975Z",
      "tileSize": "large",
      "isNFTSpace": false,
      "isCreatorToolkitSpace": false,
      "packageSKU": "",
      "worldID": "",
      "directlyInvitedGuestsArray": [],
      "active": true,
      "users": [
        "6494e59c00755e71b831b155",
        "650bcbd3997987b22b0b5785"
      ],
      "activeParticipantCount": 2,
      "likes": 311,
      "views": 6188,
      "isInstanceable": false,
      "likedSpace": false,
      "promoted": false,
      "lastPromoted": "2023-09-20T13:14:40.636267Z"
    }
  ],
  "paging": {
    "total": 1
  }
}
