{
  "rooms": [
    {
      "id": "639bc4d83b867100010cf851",
      "ownerID": "639af2c9c6355b1cd52fe516",
      "owner": {
        "userID": "639af2c9c6355b1cd52fe516",
        "displayName": "Apolostudios / Metaverse Developer"
      },
      "name": "Plaza Mayor Valladolid (Spain)-  Ferias y Fiestas Virgen San Lorenzo 2023",
      "slug": "Plaza-Mayor-Valladolid-Spain-Ferias-y-Fiestas-Virgen-San-Lorenzo-2023",
      "description": "Vive en directo el pregón, el record guiness y el espectaculo piromusical de las ferias y fiestas de Valladolid.",
      "tags": [
        "valladolid",
        "trendy",
        "party",
        "turism",
        "spain"
      ],
      "orgOwner": {
        "id": "",
        "name": "",
        "subscription": {
          "subscriptionType": "",
          "subscriptionSource": "",
          "isActive": false
        }
      },
      "organizations": null,
      "timeLastJoined": "0001-01-01T00:00:00Z",
      "thumbnails": [],
      "activeParticipants": [
        {
          "id": "639af2c9c6355b1cd52fe516",
          "displayName": "Apolostudios / Metaverse Developer",
          "profilePicURL": "https://renderapi.s3.amazonaws.com/Cb4pxJNou.png",
          "avatarData": {
            "avatarUserID": "",
            "avatarID": "",
            "avatarBody": "spatialcontent://item:s6psffI4GQJl-bfLtJawO",
            "filename": "",
            "skinColorOverride": "",
            "shirtColorOverride": "",
            "readyPlayerMeID": "",
            "readyPlayerMeAvatarID": "",
            "readyPlayerMeThumbnails": {
              "upperBody": "https://renderapi.s3.amazonaws.com/Cb4pxJNou.png",
              "lowerBody": ""
            },
            "readyPlayerMeUrl": "https://models.readyplayer.me/639af4d00eab23107f35642d.glb?updatedAt=1686746863084",
            "ReadyPlayerMeUrlLastUpdated": "0001-01-01T00:00:00Z",
            "readyPlayerMeUrlCrunched": "",
            "readyPlayerMeUrlCrunchedBrotli": "",
            "ReadyPlayerMeUrlCrunchedLastUpdated": "0001-01-01T00:00:00Z",
            "activeAvatarStyle": "CREATOR_TOOLKIT"
          },
          "appearanceCustomization": {
            "profileColor": "tan"
          },
          "clientPlatforms": [
            "Web",
            "Web",
            "Web",
            "Web",
            "Web",
            "Web",
            "Web",
            "Web",
            "Web",
            "Web"
          ],
          "permissions": []
        },
        {
          "id": "624816690ff6a86333f91aa2",
          "displayName": "michiyo_t",
          "profilePicURL": "https://renderapi.s3.amazonaws.com/v9OKMPaUK.png",
          "avatarData": {
            "avatarUserID": "",
            "avatarID": "",
            "avatarBody": "https://dd2cgqlmnwvp5.cloudfront.net/avatar_generic_bodies/rpm_female_hijab/model.glb",
            "filename": "",
            "skinColorOverride": "",
            "shirtColorOverride": "",
            "readyPlayerMeID": "",
            "readyPlayerMeAvatarID": "",
            "readyPlayerMeThumbnails": {
              "upperBody": "https://renderapi.s3.amazonaws.com/v9OKMPaUK.png",
              "lowerBody": ""
            },
            "readyPlayerMeUrl": "https://models.readyplayer.me/6464462c7ddf6268b917733e.glb?updatedAt=1684607055577",
            "ReadyPlayerMeUrlLastUpdated": "0001-01-01T00:00:00Z",
            "readyPlayerMeUrlCrunched": "",
            "readyPlayerMeUrlCrunchedBrotli": "",
            "ReadyPlayerMeUrlCrunchedLastUpdated": "0001-01-01T00:00:00Z",
            "activeAvatarStyle": "READY_PLAYER_ME"
          },
          "appearanceCustomization": {
            "profileColor": "purple"
          },
          "clientPlatforms": [
            "iOS"
          ],
          "permissions": []
        }
      ],
      "polymerVersion": 19,
      "roomThumbnails": {
        "customGetUrl": "https://cdn.spatial.io/assets/v1/thumbnails/639bc4d83b867100010cf851/customThumbnail/r/beb151b9e66587300ef78501afde046fa9b2e595eda50bbada47424b6ef9c8a4/1694323583",
        "transientGetUrl": "https://cdn.spatial.io/assets/v1/thumbnails/639bc4d83b867100010cf851/transientStateThumbnail/r/286ee16128c5eb1d6fd7d654e28cb48ce00bfa5385ee01d1741d6c4dafd95879/1694323583",
        "persistentGetUrl": "https://cdn.spatial.io/assets/v1/thumbnails/639bc4d83b867100010cf851/persistentStateThumbnail/r/797922c43235f476bbff2512545a4e11e3ad7e499307828405b1b635a91f64c3/1694323583",
        "cubemapGetUrl": "https://cdn.spatial.io/assets/v1/thumbnails/639bc4d83b867100010cf851/cubemap/r/e3fba548cf1f625d7dea3ef295bc52181f28bdf33a9290bf4e7024ba24d19267/1694323583",
        "expiresAt": 1694338272
      },
      "thumbnail": "https://cdn.spatial.io/assets/v1/thumbnails/639bc4d83b867100010cf851/customThumbnail/r/beb151b9e66587300ef78501afde046fa9b2e595eda50bbada47424b6ef9c8a4/1694323583",
      "cubeMap": "https://cdn.spatial.io/assets/v1/thumbnails/639bc4d83b867100010cf851/cubemap/r/e3fba548cf1f625d7dea3ef295bc52181f28bdf33a9290bf4e7024ba24d19267/1694323583",
      "starred": true,
      "sandbox": false,
      "shareID": "6871682445212284257",
      "code": "",
      "shareSetting": "ORG",
      "publicLink": true,
      "roomAdmins": [
        "62cfe0d21111938e99737620",
        "62cffe2bb921b8527a6a4007"
      ],
      "restrictedPermissions": [
        "RESTRICT_OTHERS_VIEW_ONLY"
      ],
      "directlyInvitedGuests": {},
      "lobbyType": "",
      "published": true,
      "defaultRoomContent": null,
      "accessible": true,
      "createdAt": "2022-12-16T01:07:36.975Z",
      "tileSize": "large",
      "isNFTSpace": false,
      "isCreatorToolkitSpace": false,
      "packageSKU": "",
      "worldID": "",
      "directlyInvitedGuestsArray": [],
      "active": true,
      "users": [
        "639af2c9c6355b1cd52fe516",
        "624816690ff6a86333f91aa2"
      ],
      "activeParticipantCount": 11,
      "likes": 261,
      "views": 4821,
      "isInstanceable": false,
      "likedSpace": false,
      "promoted": true,
      "lastPromoted": "2023-09-06T14:40:14.017529Z"
    }
  ],
  "paging": {
    "total": 1
  }
}
