{
  "rooms": [
    {
      "id": "639bc4d83b867100010cf851",
      "ownerID": "639af2c9c6355b1cd52fe516",
      "owner": {
        "userID": "639af2c9c6355b1cd52fe516",
        "displayName": "Apolostudios / Metaverse Developer"
      },
      "name": "Plaza Mayor Valladolid (Spain)-  Ferias y Fiestas Virgen San Lorenzo 2023",
      "slug": "Plaza-Mayor-Valladolid-Spain-Ferias-y-Fiestas-Virgen-San-Lorenzo-2023",
      "description": "Vive en directo el pregón, el record guiness y el espectaculo piromusical de las ferias y fiestas de Valladolid.",
      "tags": [
        "valladolid",
        "trendy",
        "party",
        "turism",
        "spain"
      ],
      "orgOwner": {
        "id": "",
        "name": "",
        "subscription": {
          "subscriptionType": "",
          "subscriptionSource": "",
          "isActive": false
        }
      },
      "organizations": null,
      "timeLastJoined": "0001-01-01T00:00:00Z",
      "thumbnails": [],
      "activeParticipants": [],
      "polymerVersion": 19,
      "roomThumbnails": {
        "customGetUrl": "https://cdn.spatial.io/assets/v1/thumbnails/639bc4d83b867100010cf851/customThumbnail/r/1030835d44c312c74b3dd4bc5d13c6ba290d5d5af441c055ed2b5eafeb06319e/1697013872",
        "transientGetUrl": "https://cdn.spatial.io/assets/v1/thumbnails/639bc4d83b867100010cf851/transientStateThumbnail/r/3d2e6d8a3bd8f11ec40356f61e57bdaf100a1db5ec364b9286925904b79f911d/1697013872",
        "persistentGetUrl": "https://cdn.spatial.io/assets/v1/thumbnails/639bc4d83b867100010cf851/persistentStateThumbnail/r/19f4789a32d05a461157cd3c967c26ca42225a6a85932d2d30f25e477a9e9ba9/1697013872",
        "cubemapGetUrl": "https://cdn.spatial.io/assets/v1/thumbnails/639bc4d83b867100010cf851/cubemap/r/e21a4d6f23b46af5feab690046b45926e870443fe9ff2cbb4867bddfb5020e7b/1697013872",
        "expiresAt": 1697028327
      },
      "thumbnail": "https://cdn.spatial.io/assets/v1/thumbnails/639bc4d83b867100010cf851/customThumbnail/r/1030835d44c312c74b3dd4bc5d13c6ba290d5d5af441c055ed2b5eafeb06319e/1697013872",
      "cubeMap": "https://cdn.spatial.io/assets/v1/thumbnails/639bc4d83b867100010cf851/cubemap/r/e21a4d6f23b46af5feab690046b45926e870443fe9ff2cbb4867bddfb5020e7b/1697013872",
      "starred": true,
      "sandbox": false,
      "shareID": "6871682445212284257",
      "code": "",
      "shareSetting": "ORG",
      "publicLink": true,
      "roomAdmins": [
        "62cfe0d21111938e99737620",
        "62cffe2bb921b8527a6a4007"
      ],
      "restrictedPermissions": [
        "RESTRICT_OTHERS_VIEW_ONLY"
      ],
      "directlyInvitedGuests": {},
      "lobbyType": "",
      "published": true,
      "defaultRoomContent": null,
      "accessible": true,
      "createdAt": "2022-12-16T01:07:36.975Z",
      "isNFTSpace": false,
      "isCreatorToolkitSpace": false,
      "packageSKU": "",
      "worldID": "",
      "directlyInvitedGuestsArray": [],
      "active": false,
      "users": [],
      "activeParticipantCount": 0,
      "likes": 338,
      "views": 9922,
      "isInstanceable": false,
      "likedSpace": false,
      "promoted": true,
      "lastPromoted": "2023-10-01T11:27:27.125745Z"
    }
  ],
  "paging": {
    "total": 1
  }
}
