{
  "rooms": [
    {
      "id": "639bc4d83b867100010cf851",
      "ownerID": "639af2c9c6355b1cd52fe516",
      "owner": {
        "userID": "639af2c9c6355b1cd52fe516",
        "displayName": "Apolostudios / Metaverse Developer"
      },
      "name": "Plaza Mayor Valladolid (Spain)-  Ferias y Fiestas Virgen San Lorenzo 2023",
      "slug": "Plaza-Mayor-Valladolid-Spain-Ferias-y-Fiestas-Virgen-San-Lorenzo-2023",
      "description": "Vive en directo el pregón, el record guiness y el espectaculo piromusical de las ferias y fiestas de Valladolid.",
      "tags": [
        "valladolid",
        "trendy",
        "party",
        "turism",
        "spain"
      ],
      "orgOwner": {
        "id": "",
        "name": "",
        "subscription": {
          "subscriptionType": "",
          "subscriptionSource": "",
          "isActive": false
        }
      },
      "organizations": null,
      "timeLastJoined": "0001-01-01T00:00:00Z",
      "thumbnails": [],
      "activeParticipants": [
        {
          "id": "650c4a4c77331e798405b044",
          "displayName": "Marian_Metaverse15",
          "profilePicURL": "",
          "avatarData": {
            "avatarUserID": "",
            "avatarID": "",
            "avatarBody": "",
            "filename": "",
            "skinColorOverride": "",
            "shirtColorOverride": "",
            "readyPlayerMeID": "",
            "readyPlayerMeAvatarID": "",
            "readyPlayerMeThumbnails": {
              "upperBody": "",
              "lowerBody": ""
            },
            "readyPlayerMeUrl": "",
            "ReadyPlayerMeUrlLastUpdated": "0001-01-01T00:00:00Z",
            "readyPlayerMeUrlCrunched": "",
            "readyPlayerMeUrlCrunchedBrotli": "",
            "ReadyPlayerMeUrlCrunchedLastUpdated": "0001-01-01T00:00:00Z",
            "activeAvatarStyle": "REALISTIC"
          },
          "appearanceCustomization": {
            "profileColor": "tan"
          },
          "clientPlatforms": [
            "Web"
          ],
          "permissions": []
        },
        {
          "id": "650c4a69c6aff1eb09c893a3",
          "displayName": "meta_sergioab80",
          "profilePicURL": "https://renderapi.s3.amazonaws.com/vxyOtqgbY.png",
          "avatarData": {
            "avatarUserID": "",
            "avatarID": "",
            "avatarBody": "https://dd2cgqlmnwvp5.cloudfront.net/avatar_generic_bodies/rpm_female_tshirt/model.glb",
            "filename": "",
            "skinColorOverride": "deb184",
            "shirtColorOverride": "8ed94f",
            "readyPlayerMeID": "",
            "readyPlayerMeAvatarID": "",
            "readyPlayerMeThumbnails": {
              "upperBody": "https://renderapi.s3.amazonaws.com/vxyOtqgbY.png",
              "lowerBody": ""
            },
            "readyPlayerMeUrl": "https://models.readyplayer.me/650c4f17910983b023e0e4b4.glb?updatedAt=1695305530507",
            "ReadyPlayerMeUrlLastUpdated": "0001-01-01T00:00:00Z",
            "readyPlayerMeUrlCrunched": "",
            "readyPlayerMeUrlCrunchedBrotli": "",
            "ReadyPlayerMeUrlCrunchedLastUpdated": "0001-01-01T00:00:00Z",
            "activeAvatarStyle": "READY_PLAYER_ME"
          },
          "appearanceCustomization": {
            "profileColor": "red"
          },
          "clientPlatforms": [
            "Web"
          ],
          "permissions": []
        },
        {
          "id": "650c4a451b74897228da4a5d",
          "displayName": "mebs83111",
          "profilePicURL": "",
          "avatarData": {
            "avatarUserID": "",
            "avatarID": "",
            "avatarBody": "",
            "filename": "",
            "skinColorOverride": "",
            "shirtColorOverride": "",
            "readyPlayerMeID": "",
            "readyPlayerMeAvatarID": "",
            "readyPlayerMeThumbnails": {
              "upperBody": "",
              "lowerBody": ""
            },
            "readyPlayerMeUrl": "",
            "ReadyPlayerMeUrlLastUpdated": "0001-01-01T00:00:00Z",
            "readyPlayerMeUrlCrunched": "",
            "readyPlayerMeUrlCrunchedBrotli": "",
            "ReadyPlayerMeUrlCrunchedLastUpdated": "0001-01-01T00:00:00Z",
            "activeAvatarStyle": "REALISTIC"
          },
          "appearanceCustomization": {
            "profileColor": "tan"
          },
          "clientPlatforms": [
            "Web"
          ],
          "permissions": []
        },
        {
          "id": "650c4a5b1b74897228da4a7c",
          "displayName": "Heraldo_Virtual",
          "profilePicURL": "https://dd2cgqlmnwvp5.cloudfront.net/avatar_generic_bodies/rpm_male_hoody/thumbnail.png",
          "avatarData": {
            "avatarUserID": "",
            "avatarID": "",
            "avatarBody": "https://dd2cgqlmnwvp5.cloudfront.net/avatar_generic_bodies/rpm_male_hoody/model.glb",
            "filename": "",
            "skinColorOverride": "",
            "shirtColorOverride": "",
            "readyPlayerMeID": "",
            "readyPlayerMeAvatarID": "",
            "readyPlayerMeThumbnails": {
              "upperBody": "",
              "lowerBody": ""
            },
            "readyPlayerMeUrl": "",
            "ReadyPlayerMeUrlLastUpdated": "0001-01-01T00:00:00Z",
            "readyPlayerMeUrlCrunched": "",
            "readyPlayerMeUrlCrunchedBrotli": "",
            "ReadyPlayerMeUrlCrunchedLastUpdated": "0001-01-01T00:00:00Z",
            "activeAvatarStyle": "REALISTIC"
          },
          "appearanceCustomization": {
            "profileColor": "orange"
          },
          "clientPlatforms": [
            "Web"
          ],
          "permissions": []
        },
        {
          "id": "650c4a4fd45ed3a7983916f1",
          "displayName": "Humberto",
          "profilePicURL": "",
          "avatarData": {
            "avatarUserID": "",
            "avatarID": "",
            "avatarBody": "",
            "filename": "",
            "skinColorOverride": "",
            "shirtColorOverride": "",
            "readyPlayerMeID": "",
            "readyPlayerMeAvatarID": "",
            "readyPlayerMeThumbnails": {
              "upperBody": "",
              "lowerBody": ""
            },
            "readyPlayerMeUrl": "",
            "ReadyPlayerMeUrlLastUpdated": "0001-01-01T00:00:00Z",
            "readyPlayerMeUrlCrunched": "",
            "readyPlayerMeUrlCrunchedBrotli": "",
            "ReadyPlayerMeUrlCrunchedLastUpdated": "0001-01-01T00:00:00Z",
            "activeAvatarStyle": "REALISTIC"
          },
          "appearanceCustomization": {
            "profileColor": "tan"
          },
          "clientPlatforms": [
            "Web"
          ],
          "permissions": []
        },
        {
          "id": "650c4a411b74897228da4a55",
          "displayName": "PaolaG",
          "profilePicURL": "https://dd2cgqlmnwvp5.cloudfront.net/avatar_generic_bodies/rpm_female_tshirt/thumbnail.png",
          "avatarData": {
            "avatarUserID": "",
            "avatarID": "",
            "avatarBody": "https://dd2cgqlmnwvp5.cloudfront.net/avatar_generic_bodies/rpm_female_tshirt/model.glb",
            "filename": "",
            "skinColorOverride": "f4ecdb",
            "shirtColorOverride": "ff2198",
            "readyPlayerMeID": "",
            "readyPlayerMeAvatarID": "",
            "readyPlayerMeThumbnails": {
              "upperBody": "",
              "lowerBody": ""
            },
            "readyPlayerMeUrl": "",
            "ReadyPlayerMeUrlLastUpdated": "0001-01-01T00:00:00Z",
            "readyPlayerMeUrlCrunched": "",
            "readyPlayerMeUrlCrunchedBrotli": "",
            "ReadyPlayerMeUrlCrunchedLastUpdated": "0001-01-01T00:00:00Z",
            "activeAvatarStyle": "REALISTIC"
          },
          "appearanceCustomization": {
            "profileColor": "orange"
          },
          "clientPlatforms": [
            "Web"
          ],
          "permissions": []
        },
        {
          "id": "650c4aa31b74897228da4b5c",
          "displayName": "cfmoram",
          "profilePicURL": "https://renderapi.s3.amazonaws.com/ED5Ps91P0.png",
          "avatarData": {
            "avatarUserID": "",
            "avatarID": "",
            "avatarBody": "https://dd2cgqlmnwvp5.cloudfront.net/avatar_generic_bodies/rpm_male_baggy_jacket/model.glb",
            "filename": "",
            "skinColorOverride": "",
            "shirtColorOverride": "",
            "readyPlayerMeID": "",
            "readyPlayerMeAvatarID": "",
            "readyPlayerMeThumbnails": {
              "upperBody": "https://renderapi.s3.amazonaws.com/ED5Ps91P0.png",
              "lowerBody": ""
            },
            "readyPlayerMeUrl": "https://models.readyplayer.me/650c4ec2910983b023e0e3f8.glb?updatedAt=1695305417163",
            "ReadyPlayerMeUrlLastUpdated": "0001-01-01T00:00:00Z",
            "readyPlayerMeUrlCrunched": "",
            "readyPlayerMeUrlCrunchedBrotli": "",
            "ReadyPlayerMeUrlCrunchedLastUpdated": "0001-01-01T00:00:00Z",
            "activeAvatarStyle": "READY_PLAYER_ME"
          },
          "appearanceCustomization": {
            "profileColor": "red"
          },
          "clientPlatforms": [
            "Web"
          ],
          "permissions": []
        },
        {
          "id": "650c4bd41b74897228da4e75",
          "displayName": "Mauricio_Meta",
          "profilePicURL": "https://renderapi.s3.amazonaws.com/NRfzQCqm6.png",
          "avatarData": {
            "avatarUserID": "",
            "avatarID": "",
            "avatarBody": "https://dd2cgqlmnwvp5.cloudfront.net/avatar_generic_bodies/rpm_male_baggy_jacket/model.glb",
            "filename": "",
            "skinColorOverride": "",
            "shirtColorOverride": "",
            "readyPlayerMeID": "",
            "readyPlayerMeAvatarID": "",
            "readyPlayerMeThumbnails": {
              "upperBody": "https://renderapi.s3.amazonaws.com/NRfzQCqm6.png",
              "lowerBody": ""
            },
            "readyPlayerMeUrl": "https://models.readyplayer.me/650c4e8de560d493958dd9c4.glb?updatedAt=1695305378780",
            "ReadyPlayerMeUrlLastUpdated": "0001-01-01T00:00:00Z",
            "readyPlayerMeUrlCrunched": "",
            "readyPlayerMeUrlCrunchedBrotli": "",
            "ReadyPlayerMeUrlCrunchedLastUpdated": "0001-01-01T00:00:00Z",
            "activeAvatarStyle": "READY_PLAYER_ME"
          },
          "appearanceCustomization": {
            "profileColor": "red"
          },
          "clientPlatforms": [
            "Web"
          ],
          "permissions": []
        },
        {
          "id": "650c4aa277331e798405b089",
          "displayName": "CarmenBe",
          "profilePicURL": "https://dd2cgqlmnwvp5.cloudfront.net/avatar_generic_bodies/rpm_female_baggy_jacket/thumbnail.png",
          "avatarData": {
            "avatarUserID": "",
            "avatarID": "",
            "avatarBody": "https://dd2cgqlmnwvp5.cloudfront.net/avatar_generic_bodies/rpm_female_baggy_jacket/model.glb",
            "filename": "",
            "skinColorOverride": "",
            "shirtColorOverride": "",
            "readyPlayerMeID": "",
            "readyPlayerMeAvatarID": "",
            "readyPlayerMeThumbnails": {
              "upperBody": "",
              "lowerBody": ""
            },
            "readyPlayerMeUrl": "",
            "ReadyPlayerMeUrlLastUpdated": "0001-01-01T00:00:00Z",
            "readyPlayerMeUrlCrunched": "",
            "readyPlayerMeUrlCrunchedBrotli": "",
            "ReadyPlayerMeUrlCrunchedLastUpdated": "0001-01-01T00:00:00Z",
            "activeAvatarStyle": "REALISTIC"
          },
          "appearanceCustomization": {
            "profileColor": "purple"
          },
          "clientPlatforms": [
            "Web"
          ],
          "permissions": []
        },
        {
          "id": "650c4e63cb4f602f1cf5b8c5",
          "displayName": "Bettylu",
          "profilePicURL": "",
          "avatarData": {
            "avatarUserID": "",
            "avatarID": "",
            "avatarBody": "",
            "filename": "",
            "skinColorOverride": "",
            "shirtColorOverride": "",
            "readyPlayerMeID": "",
            "readyPlayerMeAvatarID": "",
            "readyPlayerMeThumbnails": {
              "upperBody": "",
              "lowerBody": ""
            },
            "readyPlayerMeUrl": "",
            "ReadyPlayerMeUrlLastUpdated": "0001-01-01T00:00:00Z",
            "readyPlayerMeUrlCrunched": "",
            "readyPlayerMeUrlCrunchedBrotli": "",
            "ReadyPlayerMeUrlCrunchedLastUpdated": "0001-01-01T00:00:00Z",
            "activeAvatarStyle": "REALISTIC"
          },
          "appearanceCustomization": {
            "profileColor": "red"
          },
          "clientPlatforms": [
            "Web"
          ],
          "permissions": []
        },
        {
          "id": "650c4a5877331e798405b049",
          "displayName": "MetaProfe",
          "profilePicURL": "",
          "avatarData": {
            "avatarUserID": "",
            "avatarID": "",
            "avatarBody": "",
            "filename": "",
            "skinColorOverride": "",
            "shirtColorOverride": "",
            "readyPlayerMeID": "",
            "readyPlayerMeAvatarID": "",
            "readyPlayerMeThumbnails": {
              "upperBody": "",
              "lowerBody": ""
            },
            "readyPlayerMeUrl": "",
            "ReadyPlayerMeUrlLastUpdated": "0001-01-01T00:00:00Z",
            "readyPlayerMeUrlCrunched": "",
            "readyPlayerMeUrlCrunchedBrotli": "",
            "ReadyPlayerMeUrlCrunchedLastUpdated": "0001-01-01T00:00:00Z",
            "activeAvatarStyle": "REALISTIC"
          },
          "appearanceCustomization": {
            "profileColor": "orange"
          },
          "clientPlatforms": [
            "Web"
          ],
          "permissions": []
        }
      ],
      "polymerVersion": 19,
      "roomThumbnails": {
        "customGetUrl": "https://cdn.spatial.io/assets/v1/thumbnails/639bc4d83b867100010cf851/customThumbnail/r/b1b1fbc060c2c1ee98c7e8a9bf37767c54ed2d20e0561d3e0e8a0544aede7337/1695305662",
        "transientGetUrl": "https://cdn.spatial.io/assets/v1/thumbnails/639bc4d83b867100010cf851/transientStateThumbnail/r/c0d481c1e2f44bd506545b50f9440848daae7d83d0c227186f18f7e9dc066932/1695305662",
        "persistentGetUrl": "https://cdn.spatial.io/assets/v1/thumbnails/639bc4d83b867100010cf851/persistentStateThumbnail/r/a724773282f0dcfeca271a22cd7313c5351028331237d2ca8bf1de29fd76c5d0/1695305662",
        "cubemapGetUrl": "https://cdn.spatial.io/assets/v1/thumbnails/639bc4d83b867100010cf851/cubemap/r/3e5da2006fc0933f45dfdb46a74661f5eb05a6b474b8332a72a579a23a05fd86/1695305662",
        "expiresAt": 1695320161
      },
      "thumbnail": "https://cdn.spatial.io/assets/v1/thumbnails/639bc4d83b867100010cf851/customThumbnail/r/b1b1fbc060c2c1ee98c7e8a9bf37767c54ed2d20e0561d3e0e8a0544aede7337/1695305662",
      "cubeMap": "https://cdn.spatial.io/assets/v1/thumbnails/639bc4d83b867100010cf851/cubemap/r/3e5da2006fc0933f45dfdb46a74661f5eb05a6b474b8332a72a579a23a05fd86/1695305662",
      "starred": true,
      "sandbox": false,
      "shareID": "6871682445212284257",
      "code": "",
      "shareSetting": "ORG",
      "publicLink": true,
      "roomAdmins": [
        "62cfe0d21111938e99737620",
        "62cffe2bb921b8527a6a4007"
      ],
      "restrictedPermissions": [
        "RESTRICT_OTHERS_VIEW_ONLY"
      ],
      "directlyInvitedGuests": {},
      "lobbyType": "",
      "published": true,
      "defaultRoomContent": null,
      "accessible": true,
      "createdAt": "2022-12-16T01:07:36.975Z",
      "tileSize": "large",
      "isNFTSpace": false,
      "isCreatorToolkitSpace": false,
      "packageSKU": "",
      "worldID": "",
      "directlyInvitedGuestsArray": [],
      "active": true,
      "users": [
        "650c4a4c77331e798405b044",
        "650c4a69c6aff1eb09c893a3",
        "650c4a451b74897228da4a5d",
        "650c4a5b1b74897228da4a7c",
        "650c4a4fd45ed3a7983916f1",
        "650c4a411b74897228da4a55",
        "650c4aa31b74897228da4b5c",
        "650c4bd41b74897228da4e75",
        "650c4aa277331e798405b089",
        "650c4e63cb4f602f1cf5b8c5",
        "650c4a5877331e798405b049"
      ],
      "activeParticipantCount": 11,
      "likes": 311,
      "views": 6229,
      "isInstanceable": false,
      "likedSpace": false,
      "promoted": false,
      "lastPromoted": "2023-09-20T13:14:40.636267Z"
    }
  ],
  "paging": {
    "total": 1
  }
}
