{
  "rooms": [
    {
      "id": "639bc4d83b867100010cf851",
      "ownerID": "639af2c9c6355b1cd52fe516",
      "owner": {
        "userID": "639af2c9c6355b1cd52fe516",
        "displayName": "Apolostudios / Metaverse Developer"
      },
      "name": "Plaza Mayor Valladolid (Spain)-  Ferias y Fiestas Virgen San Lorenzo 2023",
      "slug": "Plaza-Mayor-Valladolid-Spain-Ferias-y-Fiestas-Virgen-San-Lorenzo-2023",
      "description": "Vive en directo el pregón, el record guiness y el espectaculo piromusical de las ferias y fiestas de Valladolid.",
      "tags": [
        "valladolid",
        "trendy",
        "party",
        "turism",
        "spain"
      ],
      "orgOwner": {
        "id": "",
        "name": "",
        "subscription": {
          "subscriptionType": "",
          "subscriptionSource": "",
          "isActive": false
        }
      },
      "organizations": null,
      "timeLastJoined": "0001-01-01T00:00:00Z",
      "thumbnails": [],
      "activeParticipants": [
        {
          "id": "639af2c9c6355b1cd52fe516",
          "displayName": "Apolostudios / Metaverse Developer",
          "profilePicURL": "https://renderapi.s3.amazonaws.com/Cb4pxJNou.png",
          "avatarData": {
            "avatarUserID": "",
            "avatarID": "",
            "avatarBody": "spatialcontent://item:s6psffI4GQJl-bfLtJawO",
            "filename": "",
            "skinColorOverride": "",
            "shirtColorOverride": "",
            "readyPlayerMeID": "",
            "readyPlayerMeAvatarID": "",
            "readyPlayerMeThumbnails": {
              "upperBody": "https://renderapi.s3.amazonaws.com/Cb4pxJNou.png",
              "lowerBody": ""
            },
            "readyPlayerMeUrl": "https://models.readyplayer.me/639af4d00eab23107f35642d.glb?updatedAt=1686746863084",
            "ReadyPlayerMeUrlLastUpdated": "0001-01-01T00:00:00Z",
            "readyPlayerMeUrlCrunched": "",
            "readyPlayerMeUrlCrunchedBrotli": "",
            "ReadyPlayerMeUrlCrunchedLastUpdated": "0001-01-01T00:00:00Z",
            "activeAvatarStyle": "CREATOR_TOOLKIT"
          },
          "appearanceCustomization": {
            "profileColor": "tan"
          },
          "clientPlatforms": [
            "Web",
            "Web"
          ],
          "permissions": []
        }
      ],
      "polymerVersion": 19,
      "roomThumbnails": {
        "customGetUrl": "https://cdn.spatial.io/assets/v1/thumbnails/639bc4d83b867100010cf851/customThumbnail/r/5fab3d1ad4fb67530f396fb819bc1fa5fff02a8d9f5739caff0694b283a3ac84/1695440064",
        "transientGetUrl": "https://cdn.spatial.io/assets/v1/thumbnails/639bc4d83b867100010cf851/transientStateThumbnail/r/c22393760bfcd9ba04bc8ff09fef04f5d0380d5480f5b0ed04a3dce8d30c0b0f/1695440064",
        "persistentGetUrl": "https://cdn.spatial.io/assets/v1/thumbnails/639bc4d83b867100010cf851/persistentStateThumbnail/r/19210363c885f9ab3de95e12b10a5ce24d8d63625a2f8176a28c6d7adbf20a1e/1695440064",
        "cubemapGetUrl": "https://cdn.spatial.io/assets/v1/thumbnails/639bc4d83b867100010cf851/cubemap/r/4d451db1157f66309a1142b1b90cb4acaadf3f4b7f48daa62c1f759a81d35f19/1695440064",
        "expiresAt": 1695454557
      },
      "thumbnail": "https://cdn.spatial.io/assets/v1/thumbnails/639bc4d83b867100010cf851/customThumbnail/r/5fab3d1ad4fb67530f396fb819bc1fa5fff02a8d9f5739caff0694b283a3ac84/1695440064",
      "cubeMap": "https://cdn.spatial.io/assets/v1/thumbnails/639bc4d83b867100010cf851/cubemap/r/4d451db1157f66309a1142b1b90cb4acaadf3f4b7f48daa62c1f759a81d35f19/1695440064",
      "starred": true,
      "sandbox": false,
      "shareID": "6871682445212284257",
      "code": "",
      "shareSetting": "ORG",
      "publicLink": true,
      "roomAdmins": [
        "62cfe0d21111938e99737620",
        "62cffe2bb921b8527a6a4007"
      ],
      "restrictedPermissions": [
        "RESTRICT_OTHERS_VIEW_ONLY"
      ],
      "directlyInvitedGuests": {},
      "lobbyType": "",
      "published": true,
      "defaultRoomContent": null,
      "accessible": true,
      "createdAt": "2022-12-16T01:07:36.975Z",
      "isNFTSpace": false,
      "isCreatorToolkitSpace": false,
      "packageSKU": "",
      "worldID": "",
      "directlyInvitedGuestsArray": [],
      "active": true,
      "users": [
        "639af2c9c6355b1cd52fe516"
      ],
      "activeParticipantCount": 2,
      "likes": 314,
      "views": 6346,
      "isInstanceable": false,
      "likedSpace": false,
      "promoted": true,
      "lastPromoted": "2023-09-22T22:28:37.424794Z"
    }
  ],
  "paging": {
    "total": 1
  }
}
