{
  "rooms": [
    {
      "id": "639bc4d83b867100010cf851",
      "ownerID": "639af2c9c6355b1cd52fe516",
      "owner": {
        "userID": "639af2c9c6355b1cd52fe516",
        "displayName": "Apolostudios / Metaverse Developer"
      },
      "name": "Plaza Mayor Valladolid (Spain)-  Ferias y Fiestas Virgen San Lorenzo 2023",
      "slug": "Plaza-Mayor-Valladolid-Spain-Ferias-y-Fiestas-Virgen-San-Lorenzo-2023",
      "description": "Vive en directo el pregón, el record guiness y el espectaculo piromusical de las ferias y fiestas de Valladolid.",
      "tags": [
        "valladolid",
        "trendy",
        "party",
        "turism",
        "spain"
      ],
      "orgOwner": {
        "id": "",
        "name": "",
        "subscription": {
          "subscriptionType": "",
          "subscriptionSource": "",
          "isActive": false
        }
      },
      "organizations": null,
      "timeLastJoined": "0001-01-01T00:00:00Z",
      "thumbnails": [],
      "activeParticipants": [],
      "polymerVersion": 19,
      "roomThumbnails": {
        "customGetUrl": "https://cdn2.spatial.io/assets/v1/thumbnails/639bc4d83b867100010cf851/customThumbnail/r/8a1dec3c28dbb9021ac820d2c05b680a46166d7a30adf9ccb768ea7932ece907/1699464045",
        "transientGetUrl": "https://cdn2.spatial.io/assets/v1/thumbnails/639bc4d83b867100010cf851/transientStateThumbnail/r/5f7e2d9a775e08ac2d36f3fcd9aee99134f2a6bc26780ae2e1b2f60636843ea5/1699464045",
        "persistentGetUrl": "https://cdn2.spatial.io/assets/v1/thumbnails/639bc4d83b867100010cf851/persistentStateThumbnail/r/8da1f221626e04ef5a1aee10e88416135fa2ff09c34a93de384afe2187d81cb3/1699464045",
        "cubemapGetUrl": "https://cdn2.spatial.io/assets/v1/thumbnails/639bc4d83b867100010cf851/cubemap/r/df56dba2af115baf96b6e96ba25dadc109bfeed782310b2ac68dfcdf2252cbb1/1699464045",
        "expiresAt": 1699610098
      },
      "thumbnail": "https://cdn2.spatial.io/assets/v1/thumbnails/639bc4d83b867100010cf851/customThumbnail/r/8a1dec3c28dbb9021ac820d2c05b680a46166d7a30adf9ccb768ea7932ece907/1699464045",
      "cubeMap": "https://cdn2.spatial.io/assets/v1/thumbnails/639bc4d83b867100010cf851/cubemap/r/df56dba2af115baf96b6e96ba25dadc109bfeed782310b2ac68dfcdf2252cbb1/1699464045",
      "starred": true,
      "sandbox": false,
      "shareID": "6871682445212284257",
      "code": "",
      "shareSetting": "ORG",
      "publicLink": true,
      "roomAdmins": [
        "62cfe0d21111938e99737620",
        "62cffe2bb921b8527a6a4007"
      ],
      "restrictedPermissions": [
        "RESTRICT_OTHERS_VIEW_ONLY"
      ],
      "directlyInvitedGuests": {},
      "lobbyType": "",
      "published": true,
      "defaultRoomContent": null,
      "accessible": true,
      "createdAt": "2022-12-16T01:07:36.975Z",
      "isNFTSpace": false,
      "isCreatorToolkitSpace": false,
      "packageSKU": "",
      "worldID": "",
      "directlyInvitedGuestsArray": [],
      "active": false,
      "users": [],
      "activeParticipantCount": 0,
      "likes": 340,
      "views": 10011,
      "isInstanceable": false,
      "likedSpace": false,
      "promoted": true,
      "lastPromoted": "2023-10-01T11:27:27.125745Z"
    }
  ],
  "paging": {
    "total": 1
  }
}
