{
  "rooms": [
    {
      "id": "639bc4d83b867100010cf851",
      "ownerID": "639af2c9c6355b1cd52fe516",
      "owner": {
        "userID": "639af2c9c6355b1cd52fe516",
        "displayName": "Apolostudios / Metaverse Developer"
      },
      "name": "Plaza Mayor Valladolid (Spain)-  Ferias y Fiestas Virgen San Lorenzo 2023",
      "slug": "Plaza-Mayor-Valladolid-Spain-Ferias-y-Fiestas-Virgen-San-Lorenzo-2023",
      "description": "Vive en directo el pregón, el record guiness y el espectaculo piromusical de las ferias y fiestas de Valladolid.",
      "tags": [
        "valladolid",
        "trendy",
        "party",
        "turism",
        "spain"
      ],
      "orgOwner": {
        "id": "",
        "name": "",
        "subscription": {
          "subscriptionType": "",
          "subscriptionSource": "",
          "isActive": false
        }
      },
      "organizations": null,
      "timeLastJoined": "0001-01-01T00:00:00Z",
      "thumbnails": [],
      "activeParticipants": [
        {
          "id": "639af2c9c6355b1cd52fe516",
          "displayName": "Apolostudios / Metaverse Developer",
          "profilePicURL": "https://renderapi.s3.amazonaws.com/Cb4pxJNou.png",
          "avatarData": {
            "avatarUserID": "",
            "avatarID": "",
            "avatarBody": "spatialcontent://item:s6psffI4GQJl-bfLtJawO",
            "filename": "",
            "skinColorOverride": "",
            "shirtColorOverride": "",
            "readyPlayerMeID": "",
            "readyPlayerMeAvatarID": "",
            "readyPlayerMeThumbnails": {
              "upperBody": "https://renderapi.s3.amazonaws.com/Cb4pxJNou.png",
              "lowerBody": ""
            },
            "readyPlayerMeUrl": "https://models.readyplayer.me/639af4d00eab23107f35642d.glb?updatedAt=1686746863084",
            "ReadyPlayerMeUrlLastUpdated": "0001-01-01T00:00:00Z",
            "readyPlayerMeUrlCrunched": "",
            "readyPlayerMeUrlCrunchedBrotli": "",
            "ReadyPlayerMeUrlCrunchedLastUpdated": "0001-01-01T00:00:00Z",
            "activeAvatarStyle": "CREATOR_TOOLKIT"
          },
          "appearanceCustomization": {
            "profileColor": "tan"
          },
          "clientPlatforms": [
            "Web",
            "Web",
            "Web",
            "Web",
            "Web",
            "Web",
            "Web",
            "Web",
            "Web",
            "Web"
          ],
          "permissions": []
        }
      ],
      "polymerVersion": 19,
      "roomThumbnails": {
        "customGetUrl": "https://cdn.spatial.io/assets/v1/thumbnails/639bc4d83b867100010cf851/customThumbnail/r/983f22ef8272c1f3824ab9099a29559f12cd113bf90b15af6528feb5de291edc/1694386478",
        "transientGetUrl": "https://cdn.spatial.io/assets/v1/thumbnails/639bc4d83b867100010cf851/transientStateThumbnail/r/16916b6faba8054733f7128e5d8bf8775075c90c7ca33070f79fdeb3807af40d/1694386478",
        "persistentGetUrl": "https://cdn.spatial.io/assets/v1/thumbnails/639bc4d83b867100010cf851/persistentStateThumbnail/r/58830910a7fe714090c74837f54ae525cec19c43d61616fde438e1cbb6970dfd/1694386478",
        "cubemapGetUrl": "https://cdn.spatial.io/assets/v1/thumbnails/639bc4d83b867100010cf851/cubemap/r/5c57bfa15dbb1801827d2141e2b5299b99b9d243fd668281944bc9af9686d0d6/1694386478",
        "expiresAt": 1694401211
      },
      "thumbnail": "https://cdn.spatial.io/assets/v1/thumbnails/639bc4d83b867100010cf851/customThumbnail/r/983f22ef8272c1f3824ab9099a29559f12cd113bf90b15af6528feb5de291edc/1694386478",
      "cubeMap": "https://cdn.spatial.io/assets/v1/thumbnails/639bc4d83b867100010cf851/cubemap/r/5c57bfa15dbb1801827d2141e2b5299b99b9d243fd668281944bc9af9686d0d6/1694386478",
      "starred": true,
      "sandbox": false,
      "shareID": "6871682445212284257",
      "code": "",
      "shareSetting": "ORG",
      "publicLink": true,
      "roomAdmins": [
        "62cfe0d21111938e99737620",
        "62cffe2bb921b8527a6a4007"
      ],
      "restrictedPermissions": [
        "RESTRICT_OTHERS_VIEW_ONLY"
      ],
      "directlyInvitedGuests": {},
      "lobbyType": "",
      "published": true,
      "defaultRoomContent": null,
      "accessible": true,
      "createdAt": "2022-12-16T01:07:36.975Z",
      "isNFTSpace": false,
      "isCreatorToolkitSpace": false,
      "packageSKU": "",
      "worldID": "",
      "directlyInvitedGuestsArray": [],
      "active": true,
      "users": [
        "639af2c9c6355b1cd52fe516"
      ],
      "activeParticipantCount": 10,
      "likes": 263,
      "views": 4913,
      "isInstanceable": false,
      "likedSpace": false,
      "promoted": true,
      "lastPromoted": "2023-09-06T14:40:14.017529Z"
    }
  ],
  "paging": {
    "total": 1
  }
}
