{
  "rooms": [
    {
      "id": "639bc4d83b867100010cf851",
      "ownerID": "639af2c9c6355b1cd52fe516",
      "owner": {
        "userID": "639af2c9c6355b1cd52fe516",
        "displayName": "Apolostudios / Metaverse Developer"
      },
      "name": "Plaza Mayor Valladolid (Spain)-  Ferias y Fiestas Virgen San Lorenzo 2023",
      "slug": "Plaza-Mayor-Valladolid-Spain-Ferias-y-Fiestas-Virgen-San-Lorenzo-2023",
      "description": "Vive en directo el pregón, el record guiness y el espectaculo piromusical de las ferias y fiestas de Valladolid.",
      "tags": [
        "valladolid",
        "trendy",
        "party",
        "turism",
        "spain"
      ],
      "orgOwner": {
        "id": "",
        "name": "",
        "subscription": {
          "subscriptionType": "",
          "subscriptionSource": "",
          "isActive": false
        }
      },
      "organizations": null,
      "timeLastJoined": "0001-01-01T00:00:00Z",
      "thumbnails": [],
      "activeParticipants": [
        {
          "id": "64ffd7d0b8d4667501ac297e",
          "displayName": "Nattakarn Jitsaman",
          "profilePicURL": "https://dd2cgqlmnwvp5.cloudfront.net/avatar_generic_bodies/rpm_female_hijab/thumbnail.png",
          "avatarData": {
            "avatarUserID": "",
            "avatarID": "",
            "avatarBody": "https://dd2cgqlmnwvp5.cloudfront.net/avatar_generic_bodies/rpm_female_hijab/model.glb",
            "filename": "",
            "skinColorOverride": "f3eddb",
            "shirtColorOverride": "6d4e38",
            "readyPlayerMeID": "",
            "readyPlayerMeAvatarID": "",
            "readyPlayerMeThumbnails": {
              "upperBody": "",
              "lowerBody": ""
            },
            "readyPlayerMeUrl": "",
            "ReadyPlayerMeUrlLastUpdated": "0001-01-01T00:00:00Z",
            "readyPlayerMeUrlCrunched": "",
            "readyPlayerMeUrlCrunchedBrotli": "",
            "ReadyPlayerMeUrlCrunchedLastUpdated": "0001-01-01T00:00:00Z",
            "activeAvatarStyle": "REALISTIC"
          },
          "appearanceCustomization": {
            "profileColor": "green"
          },
          "clientPlatforms": [
            "Web"
          ],
          "permissions": []
        },
        {
          "id": "64fe7f402063d74ae4ef4707",
          "displayName": "Abby",
          "profilePicURL": "",
          "avatarData": {
            "avatarUserID": "",
            "avatarID": "",
            "avatarBody": "https://dd2cgqlmnwvp5.cloudfront.net/authless-rpm-avatars/female-brown-dress-shirt-638905a559d13f203a31be11/638905a559d13f203a31be11.glb",
            "filename": "",
            "skinColorOverride": "",
            "shirtColorOverride": "",
            "readyPlayerMeID": "",
            "readyPlayerMeAvatarID": "",
            "readyPlayerMeThumbnails": {
              "upperBody": "",
              "lowerBody": ""
            },
            "readyPlayerMeUrl": "",
            "ReadyPlayerMeUrlLastUpdated": "0001-01-01T00:00:00Z",
            "readyPlayerMeUrlCrunched": "",
            "readyPlayerMeUrlCrunchedBrotli": "",
            "ReadyPlayerMeUrlCrunchedLastUpdated": "0001-01-01T00:00:00Z",
            "activeAvatarStyle": "READY_PLAYER_ME"
          },
          "appearanceCustomization": {
            "profileColor": "green"
          },
          "clientPlatforms": [
            "Android"
          ],
          "permissions": []
        }
      ],
      "polymerVersion": 19,
      "roomThumbnails": {
        "customGetUrl": "https://cdn.spatial.io/assets/v1/thumbnails/639bc4d83b867100010cf851/customThumbnail/r/369b9e9ed794510f4bbefeddf6e85d78891eecaa3c40a4256967e5d6e8586384/1694489499",
        "transientGetUrl": "https://cdn.spatial.io/assets/v1/thumbnails/639bc4d83b867100010cf851/transientStateThumbnail/r/745def6eaacea298539e40db7889c51d0a7416320bf5aa8d1cc8a890dc54f283/1694489499",
        "persistentGetUrl": "https://cdn.spatial.io/assets/v1/thumbnails/639bc4d83b867100010cf851/persistentStateThumbnail/r/3e0e6d88141341b8412ce78337df27a07132d1772df3e6e42157dd2a814c34b9/1694489499",
        "cubemapGetUrl": "https://cdn.spatial.io/assets/v1/thumbnails/639bc4d83b867100010cf851/cubemap/r/5975aa48f2ae53f08e74466a24dd7729665373979a7e47c400f6a51f986a2b59/1694489499",
        "expiresAt": 1694503914
      },
      "thumbnail": "https://cdn.spatial.io/assets/v1/thumbnails/639bc4d83b867100010cf851/customThumbnail/r/369b9e9ed794510f4bbefeddf6e85d78891eecaa3c40a4256967e5d6e8586384/1694489499",
      "cubeMap": "https://cdn.spatial.io/assets/v1/thumbnails/639bc4d83b867100010cf851/cubemap/r/5975aa48f2ae53f08e74466a24dd7729665373979a7e47c400f6a51f986a2b59/1694489499",
      "starred": true,
      "sandbox": false,
      "shareID": "6871682445212284257",
      "code": "",
      "shareSetting": "ORG",
      "publicLink": true,
      "roomAdmins": [
        "62cfe0d21111938e99737620",
        "62cffe2bb921b8527a6a4007"
      ],
      "restrictedPermissions": [
        "RESTRICT_OTHERS_VIEW_ONLY"
      ],
      "directlyInvitedGuests": {},
      "lobbyType": "",
      "published": true,
      "defaultRoomContent": null,
      "accessible": true,
      "createdAt": "2022-12-16T01:07:36.975Z",
      "tileSize": "large",
      "isNFTSpace": false,
      "isCreatorToolkitSpace": false,
      "packageSKU": "",
      "worldID": "",
      "directlyInvitedGuestsArray": [],
      "active": true,
      "users": [
        "6392e3fdb0b345fa96e0a374",
        "64ffd7d0b8d4667501ac297e",
        "64fe7f402063d74ae4ef4707"
      ],
      "activeParticipantCount": 3,
      "likes": 269,
      "views": 5067,
      "isInstanceable": false,
      "likedSpace": false,
      "promoted": false,
      "lastPromoted": "2023-09-06T14:40:14.017529Z"
    }
  ],
  "paging": {
    "total": 1
  }
}
