{
  "rooms": [
    {
      "id": "639bc4d83b867100010cf851",
      "ownerID": "639af2c9c6355b1cd52fe516",
      "owner": {
        "userID": "639af2c9c6355b1cd52fe516",
        "displayName": "Apolostudios / Metaverse Developer"
      },
      "name": "Valladolid (Spain)",
      "slug": "Valladolid-Spain",
      "description": "Vive en directo el pregón, el record guiness y el espectaculo piromusical de las ferias y fiestas de Valladolid.",
      "tags": [
        "valladolid",
        "trendy",
        "party",
        "turism",
        "spain"
      ],
      "orgOwner": {
        "id": "",
        "name": "",
        "subscription": {
          "subscriptionType": "",
          "subscriptionSource": "",
          "isActive": false
        }
      },
      "organizations": null,
      "timeLastJoined": "0001-01-01T00:00:00Z",
      "thumbnails": [],
      "activeParticipants": [],
      "polymerVersion": 19,
      "roomThumbnails": {
        "customGetUrl": "https://cdn2.spatial.io/assets/v1/thumbnails/639bc4d83b867100010cf851/customThumbnail/r/ad9a17df14109eec7744ba560e0123418dc551397fbe02412345a35d23ffb3f2/1718785849",
        "transientGetUrl": "https://cdn2.spatial.io/assets/v1/thumbnails/639bc4d83b867100010cf851/transientStateThumbnail/r/8a8f672d9d50176b12fcc172b9193ea4ccf556a02a887a93d76b8f662d5a7d5b/1718785849",
        "persistentGetUrl": "https://cdn2.spatial.io/assets/v1/thumbnails/639bc4d83b867100010cf851/persistentStateThumbnail/r/b8c42888619c26086e69fde0531109cd2f44a3f83a3f375189485193f3a306ce/1718785849",
        "cubemapGetUrl": "https://cdn2.spatial.io/assets/v1/thumbnails/639bc4d83b867100010cf851/cubemap/r/7cc745804a82a265ae4a9274dcbd296e86af1b6f0a5deeda57da167f24fe3a6b/1718785849",
        "expiresAt": 1718800331
      },
      "thumbnail": "https://cdn2.spatial.io/assets/v1/thumbnails/639bc4d83b867100010cf851/customThumbnail/r/ad9a17df14109eec7744ba560e0123418dc551397fbe02412345a35d23ffb3f2/1718785849",
      "cubeMap": "https://cdn2.spatial.io/assets/v1/thumbnails/639bc4d83b867100010cf851/cubemap/r/7cc745804a82a265ae4a9274dcbd296e86af1b6f0a5deeda57da167f24fe3a6b/1718785849",
      "starred": true,
      "sandbox": false,
      "shareID": "6871682445212284257",
      "code": "",
      "shareSetting": "ORG",
      "publicLink": true,
      "roomAdmins": [
        "62cfe0d21111938e99737620",
        "62cffe2bb921b8527a6a4007"
      ],
      "restrictedPermissions": [
        "RESTRICT_OTHERS_VIEW_ONLY"
      ],
      "directlyInvitedGuests": {},
      "lobbyType": "",
      "published": true,
      "defaultRoomContent": null,
      "accessible": true,
      "createdAt": "2022-12-16T01:07:36.975Z",
      "isNFTSpace": false,
      "isCreatorToolkitSpace": false,
      "packageSKU": "",
      "worldID": "",
      "directlyInvitedGuestsArray": [],
      "active": false,
      "users": [],
      "activeParticipantCount": 0,
      "likes": 351,
      "views": 10314,
      "isInstanceable": false,
      "likedSpace": false,
      "promoted": true,
      "lastPromoted": "2023-10-01T11:27:27.125745Z"
    }
  ],
  "paging": {
    "total": 1
  }
}
